rlzoo/__init__.py
rlzoo/run_rlzoo.py
rlzoo/algorithms/__init__.py
rlzoo/algorithms/a3c/__init__.py
rlzoo/algorithms/a3c/a3c.py
rlzoo/algorithms/a3c/default.py
rlzoo/algorithms/a3c/run_a3c.py
rlzoo/algorithms/ac/__init__.py
rlzoo/algorithms/ac/ac.py
rlzoo/algorithms/ac/default.py
rlzoo/algorithms/ac/run_ac.py
rlzoo/algorithms/ddpg/__init__.py
rlzoo/algorithms/ddpg/ddpg.py
rlzoo/algorithms/ddpg/default.py
rlzoo/algorithms/ddpg/run_ddpg.py
rlzoo/algorithms/dppo/__init__.py
rlzoo/algorithms/dppo/default.py
rlzoo/algorithms/dppo/dppo.py
rlzoo/algorithms/dppo_clip/__init__.py
rlzoo/algorithms/dppo_clip/dppo_clip.py
rlzoo/algorithms/dppo_clip/run_dppo_clip.py
rlzoo/algorithms/dppo_penalty/__init__.py
rlzoo/algorithms/dppo_penalty/dppo_penalty.py
rlzoo/algorithms/dppo_penalty/run_dppo_penalty.py
rlzoo/algorithms/dqn/__init__.py
rlzoo/algorithms/dqn/default.py
rlzoo/algorithms/dqn/dqn.py
rlzoo/algorithms/dqn/run_dqn.py
rlzoo/algorithms/pg/__init__.py
rlzoo/algorithms/pg/default.py
rlzoo/algorithms/pg/pg.py
rlzoo/algorithms/pg/run_pg.py
rlzoo/algorithms/ppo/__init__.py
rlzoo/algorithms/ppo/default.py
rlzoo/algorithms/ppo/ppo.py
rlzoo/algorithms/ppo_clip/__init__.py
rlzoo/algorithms/ppo_clip/ppo_clip.py
rlzoo/algorithms/ppo_clip/run_ppo_clip.py
rlzoo/algorithms/ppo_penalty/__init__.py
rlzoo/algorithms/ppo_penalty/ppo_penalty.py
rlzoo/algorithms/ppo_penalty/run_ppo_penalty.py
rlzoo/algorithms/sac/__init__.py
rlzoo/algorithms/sac/default.py
rlzoo/algorithms/sac/run_sac.py
rlzoo/algorithms/sac/sac.py
rlzoo/algorithms/td3/__init__.py
rlzoo/algorithms/td3/default.py
rlzoo/algorithms/td3/run_td3.py
rlzoo/algorithms/td3/td3.py
rlzoo/algorithms/trpo/__init__.py
rlzoo/algorithms/trpo/default.py
rlzoo/algorithms/trpo/run_trpo.py
rlzoo/algorithms/trpo/trpo.py
rlzoo/common/__init__.py
rlzoo/common/basic_nets.py
rlzoo/common/buffer.py
rlzoo/common/build_rlbench_env.py
rlzoo/common/distributions.py
rlzoo/common/env_list.py
rlzoo/common/env_wrappers.py
rlzoo/common/math_utils.py
rlzoo-1.0.4.dist-info/LICENSE.txt
rlzoo-1.0.4.dist-info/METADATA
rlzoo-1.0.4.dist-info/WHEEL
rlzoo-1.0.4.dist-info/top_level.txt
rlzoo-1.0.4.dist-info/RECORD
